{
  "rag_rules": [
    "Place assume/guarantee declarations in component type annexes when they describe interface behavior.",
    "Use visible identifiers from the current component scope to ensure AGREE expression validity."
  ],
  "generic_rules": [
    "AGREE annex blocks must be scoped to their owning component declaration.",
    "Constants and equations in AGREE should reference only identifiers visible in the current scope.",
    "Assignments in AGREE are valid only in implementation scopes.",
    "Assumptions and guarantees should be placed in component type contracts when they refer to component ports."
  ],
  "syntax_or_pattern_reminders": [
    "AGREE contracts are enclosed in `annex agree {** ... **};` blocks.",
    "Use `assume \"label\": expression;` and `guarantee \"label\": expression;` for behavioral contracts."
  ],
  "anti_patterns": [
    "Do not place implementation-level bindings like `assign` in component type scopes.",
    "Avoid referencing identifiers not present in the current component's visible scope."
  ],
  "irrelevant_topics": [
    "AADL property associations as AGREE variables",
    "Model fusion and architecture redesign",
    "Validator diagnostics and repair actions"
  ]
}