{
  "rag_rules": [
    "Use `assume` and `guarantee` statements to express signal flow and timing constraints in AGREE annex blocks.",
    "Apply `assign` only for output features or declared auxiliary variables in implementation scope."
  ],
  "generic_rules": [
    "Place input assumptions and output guarantees in component type contracts only when concrete bounds or visible relations are provided.",
    "Treat each AGREE annex block as scoped to its owning component."
  ],
  "syntax_or_pattern_reminders": [
    "Use `assume \"label\": expression;` and `guarantee \"label\": expression;` for contract statements.",
    "Use `assign output = expression;` for output assignments in implementation scope."
  ],
  "anti_patterns": [
    "Do not place guarantee statements in implementation scope; use only assume and eq for such contexts.",
    "Do not use `guarantee` for output ranges without concrete bounds or visible relations."
  ],
  "irrelevant_topics": [
    "model traceability",
    "requirement semantics",
    "validator diagnostics",
    "model fusion rules"
  ]
}