{
  "problems": [
    {
      "diagnostic": "line 25: The first and second arguments of the 'prev' function are of non-matching types 'IntTypeDef' and 'ErrorTypeDef'",
      "cause": "type mismatch in prev() function usage",
      "minimal_edit": "replace `mode > prev(mode)` with `mode >= prev(mode) and mode != prev(mode)`"
    }
  ],
  "repair_mode": "edit_annex",
  "executor_steps": [
    "Edit the monotonic_mode guarantee in the AGREE annex to use a valid comparison with explicit inequality",
    "Replace the expression `mode > prev(mode)` with `mode >= prev(mode) and mode != prev(mode)` to ensure type consistency and logical correctness"
  ]
}