{
  "rag_rules": [
    "Place AGREE annex blocks in component type annexes for assumptions and guarantees, and in implementation annexes for bindings.",
    "Use visible feature names and concrete bounds when defining input assumptions and output guarantees."
  ],
  "generic_rules": [
    "AGREE contracts must be enclosed in `annex agree {** ... **};` blocks.",
    "Assumptions define environmental constraints; guarantees define system behavior.",
    "Ensure type consistency between declarations and expressions in AGREE contracts.",
    "Use named constants or visible relations to specify legal ranges for features."
  ],
  "syntax_or_pattern_reminders": [
    "Declare boolean helper equations using `eq name : bool = ...;` for range checks.",
    "Wrap AGREE contract content in `**` delimiters within the annex block."
  ],
  "anti_patterns": [
    "Avoid placing AGREE annex content in system implementations without proper scope alignment.",
    "Do not mix incompatible types in AGREE expressions (e.g., real vs int)."
  ],
  "irrelevant_topics": [
    "requirement traceability",
    "validator diagnostics",
    "repair patterns",
    "model analyst component extraction"
  ]
}