{
  "problems": [
    {
      "diagnostic": "Couldn't resolve reference to 'const_tar_speed'.",
      "cause": "const_tar_speed is not declared or visible in the AGREE annex context",
      "minimal_edit": "Remove or replace 'const_tar_speed' with a valid boolean expression or declaration"
    },
    {
      "diagnostic": "Couldn't resolve reference to 'abs'.",
      "cause": "abs function is not recognized in AGREE context",
      "minimal_edit": "Replace 'abs' with a valid AGREE expression or remove the expression"
    },
    {
      "diagnostic": "The types of 'Target_Speed' and 'Target' do not match.",
      "cause": "Port name mismatch in connection declaration",
      "minimal_edit": "Change 'CNTRL.Target' to 'CNTRL.Target_Speed' to match the port name"
    },
    {
      "diagnostic": "'Actual' and 'Actual_Speed' have incompatible classifiers.",
      "cause": "Port name mismatch in connection declaration",
      "minimal_edit": "Change 'THROT.Actual' to 'THROT.Actual_Speed' to match the port name"
    },
    {
      "diagnostic": "'State_Out' and 'State_Signal' have incompatible classifiers.",
      "cause": "Port name mismatch in connection declaration",
      "minimal_edit": "Change 'SM.State_Out' to 'SM.State_Signal' to match the port name"
    }
  ],
  "repair_mode": "edit_annex",
  "executor_steps": [
    "Remove or replace 'const_tar_speed' with a valid boolean expression or declaration in the AGREE annex",
    "Replace 'abs' with a valid AGREE expression or remove the expression in the AGREE annex",
    "Change 'CNTRL.Target' to 'CNTRL.Target_Speed' in the connection declaration",
    "Change 'THROT.Actual' to 'THROT.Actual_Speed' in the connection declaration",
    "Change 'SM.State_Out' to 'SM.State_Signal' in the connection declaration"
  ]
}