{
  "problems": [
    {
      "diagnostic": "Expression for assume statement is of type 'int' but must be of type 'bool'",
      "cause": "The assume statement is using an equality operator (=) which returns an integer type, not a boolean type.",
      "minimal_edit": "Change the equality operator (=) to a comparison operator (==) to return a boolean type."
    },
    {
      "diagnostic": "mismatched character '<EOF>' expecting '''",
      "cause": "The assume statement is missing a closing semicolon.",
      "minimal_edit": "Add a semicolon at the end of the assume statement."
    }
  ],
  "repair_mode": "edit_annex",
  "executor_steps": [
    "Change the equality operator (=) to a comparison operator (==) in the assume statement 'nearestIntruderAltitude_constant'.",
    "Add a semicolon at the end of the assume statement 'nearestIntruderAltitude_constant'."
  ]
}