{
  "problems": [
    {
      "diagnostic": "line 210: Couldn't resolve reference to 'ACC_INPUT_PC1'.",
      "cause": "ACC_INPUT_PC1 is a connection, not a variable or port expression in the AGREE context",
      "minimal_edit": "Replace ACC_INPUT_PC1 with acc_in_data_x in the assume statement"
    },
    {
      "diagnostic": "line 211: Couldn't resolve reference to 'ACC_INPUT_PC2'.",
      "cause": "ACC_INPUT_PC2 is a connection, not a variable or port expression in the AGREE context",
      "minimal_edit": "Replace ACC_INPUT_PC2 with acc_in_data_y in the assume statement"
    },
    {
      "diagnostic": "line 212: Couldn't resolve reference to 'ACC_INPUT_PC1'.",
      "cause": "ACC_INPUT_PC1 is a connection, not a variable or port expression in the AGREE context",
      "minimal_edit": "Replace ACC_INPUT_PC1 with accelero_thread.acc_in_data_x in the guarantee statement"
    },
    {
      "diagnostic": "line 213: Couldn't resolve reference to 'ACC_INPUT_PC2'.",
      "cause": "ACC_INPUT_PC2 is a connection, not a variable or port expression in the AGREE context",
      "minimal_edit": "Replace ACC_INPUT_PC2 with accelero_thread.acc_in_data_y in the guarantee statement"
    }
  ],
  "repair_mode": "edit_annex",
  "executor_steps": [
    "Replace ACC_INPUT_PC1 with acc_in_data_x in assume statement on line 210",
    "Replace ACC_INPUT_PC2 with acc_in_data_y in assume statement on line 211",
    "Replace ACC_INPUT_PC1 with accelero_thread.acc_in_data_x in guarantee statement on line 212",
    "Replace ACC_INPUT_PC2 with accelero_thread.acc_in_data_y in guarantee statement on line 213"
  ]
}