{
  "problems": [
    {
      "diagnostic": "line 56: Couldn't resolve reference to 'tempin1'.",
      "cause": "AGREE annex is in system implementation scope but references component type features directly",
      "minimal_edit": "Move the AGREE annex from system implementation voter.impl to system voter"
    },
    {
      "diagnostic": "line 57: Couldn't resolve reference to 'tempin2'.",
      "cause": "AGREE annex is in system implementation scope but references component type features directly",
      "minimal_edit": "Move the AGREE annex from system implementation voter.impl to system voter"
    },
    {
      "diagnostic": "line 58: Couldn't resolve reference to 'tempin1'.",
      "cause": "AGREE annex is in system implementation scope but references component type features directly",
      "minimal_edit": "Move the AGREE annex from system implementation voter.impl to system voter"
    },
    {
      "diagnostic": "line 59: Couldn't resolve reference to 'tempin2'.",
      "cause": "AGREE annex is in system implementation scope but references component type features directly",
      "minimal_edit": "Move the AGREE annex from system implementation voter.impl to system voter"
    }
  ],
  "repair_mode": "edit_full_model",
  "executor_steps": [
    "Remove the AGREE annex block from system implementation voter.impl",
    "Add the AGREE annex block to system voter",
    "Ensure all references in the AGREE annex use only visible identifiers from the component type scope"
  ]
}