{
  "problems": [
    {
      "diagnostic": "parsing Package_Specification, Empty packages are not allowed",
      "cause": "Empty package definition",
      "minimal_edit": "Remove the empty package definition."
    },
    {
      "diagnostic": "Cannot parse AADL specifications",
      "cause": "Invalid AADL syntax",
      "minimal_edit": "Correct the AADL syntax errors."
    }
  ],
  "repair_mode": "edit_full_model",
  "executor_steps": [
    "Identify and remove the empty package definition in the AADL model.",
    "Correct any AADL syntax errors to ensure the model can be parsed."
  ]
}