{
  "problems": [
    {
      "diagnostic": "/CaseProject/modified_model.aadl | line 12: missing EOF at 'var'",
      "cause": "AGREE annex syntax error: 'var' keyword is not recognized in the current context because the annex is incorrectly placed at the component type level without proper enclosing structure or because of malformed annex syntax.",
      "minimal_edit": "Move the entire AGREE annex block from the component type (GCAS_singleton) to the implementation (GCAS_singleton.impl)"
    }
  ],
  "repair_mode": "edit_full_model",
  "executor_steps": [
    "Delete the AGREE annex block from line 10-19 in component type GCAS_singleton",
    "Add the same AGREE annex block inside the system implementation GCAS_singleton.impl",
    "Ensure the annex block is syntactically valid within the implementation context",
    "Verify that all identifiers (t, height, minHeightAllowed, timeToRecovery) are legally referenced in implementation scope"
  ]
}