{
  "rag_rules": [],
  "generic_rules": [
    "Place contracts in the correct scope: component type for general properties, implementation for bindings.",
    "Use visible identifiers only when writing AGREE contracts.",
    "Ensure AGREE expressions align with AADL types (bool, int, real)."
  ],
  "syntax_or_pattern_reminders": [
    "AGREE contracts are enclosed in `annex agree { ... };` blocks.",
    "Use `assume`, `guarantee`, `eq`, and `const` keywords for contract elements."
  ],
  "anti_patterns": [
    "Do not use AADL property names (e.g., Compute_Execution_Time) directly in AGREE expressions without corresponding ports or constants.",
    "Avoid referencing implementation-level details in component type contracts."
  ],
  "irrelevant_topics": [
    "AGREE clause selection",
    "validator diagnostics",
    "repair patterns"
  ]
}