{
  "rag_rules": [
    "Place AGREE contracts within `annex agree {** ... **};` blocks, using component type annexes for general contracts and implementation annexes for implementation-level bindings.",
    "Implementation-level assignments should be placed in implementation scopes after relevant subcomponents and connections."
  ],
  "generic_rules": [
    "Prioritize AADL model structure as the source of truth for component names, ports, and connections.",
    "Use `assign` only for existing output features or declared auxiliary variables in implementation contracts.",
    "Output dependency guarantees should relate visible outputs to visible inputs."
  ],
  "syntax_or_pattern_reminders": [
    "Ensure AGREE contracts are placed within the correct scope (component type vs. implementation).",
    "Refer to AADL ports through valid variables or outputs in component type contracts."
  ],
  "anti_patterns": [
    "Do not use implementation-only subcomponent paths in component type annexes.",
    "Avoid encoding AADL properties (e.g., Compute_Execution_Time) directly as AGREE variables.",
    "Do not attempt to encode AADL event ports as numeric values in AGREE expressions without a model-provided data value."
  ],
  "irrelevant_topics": [
    "AGREE clause generation",
    "AGREE assume/guarantee syntax",
    "validator diagnostics",
    "repair patterns"
  ]
}