{
  "rag_rules": [
    "Place AGREE assumptions and guarantees in component type scopes for port references, and in implementation scopes for subcomponent bindings.",
    "Use visible feature names and concrete bounds for range assumptions and guarantees in component type contracts."
  ],
  "generic_rules": [
    "Formulate range guarantees using boolean helper declarations for clarity and reuse.",
    "Ensure type consistency between helper declarations and expressions in AGREE contracts."
  ],
  "syntax_or_pattern_reminders": [
    "Use `eq` for boolean helper declarations in AGREE: `eq var_name : bool = condition;`",
    "Wrap AGREE annex content in `annex agree { ... };` blocks with proper scoping."
  ],
  "anti_patterns": [
    "Avoid placing implementation-level bindings in component type scopes.",
    "Do not use subcomponent ports directly in type-level contracts without proper variable representation."
  ],
  "irrelevant_topics": [
    "model traceability",
    "requirement semantics",
    "validator diagnostics",
    "model fusion rules"
  ]
}