{
  "rag_rules": [],
  "generic_rules": [
    "Preserve AADL architecture when inserting AGREE annex blocks",
    "Component type annexes are for assumptions, guarantees, constants, and equation declarations",
    "Implementation annexes are for implementation-level bindings like assignments"
  ],
  "syntax_or_pattern_reminders": [
    "AGREE contracts are written inside `annex agree {**... **};` blocks"
  ],
  "anti_patterns": [
    "Do not use subcomponent ports in a component type contract unless represented through valid variables or outputs"
  ],
  "irrelevant_topics": [
    "AGREE syntax notes",
    "Defensive rules for diagnostics and validator-driven repairs"
  ]
}