{
  "rag_rules": [
    "Place AGREE annexes in component type scopes for assumptions, guarantees, constants, and equations; use implementation scopes for implementation-level bindings.",
    "Ensure AGREE contracts use valid scopes: component type for general properties, implementation for bindings."
  ],
  "generic_rules": [
    "Preserve AADL architecture when inserting AGREE annex blocks.",
    "AGREE contracts should relate visible inputs to visible outputs.",
    "Avoid using implementation-only subcomponent paths in component type annexes."
  ],
  "syntax_or_pattern_reminders": [
    "AGREE contracts are enclosed in `annex agree { ... };` blocks.",
    "Use `assume \"label\": expression;` and `guarantee \"label\": expression;` for contracts.",
    "Declare AGREE types as `int`, `real`, or `bool`."
  ],
  "anti_patterns": [
    "Do not use AADL property names (e.g., Compute_Execution_Time) directly as AGREE variables.",
    "Avoid type mismatches in AGREE expressions (e.g., comparing an int to a bool)."
  ],
  "irrelevant_topics": [
    "AGREE repair patterns",
    "validator diagnostics",
    "requirement semantics",
    "model traceability"
  ]
}