{
  "rag_rules": [
    "Use `assume` and `guarantee` clauses with descriptive labels for requirement expressions.",
    "Place input assumptions and output guarantees in the annex agree block when concrete bounds or visible features are provided."
  ],
  "generic_rules": [
    "Declare helper equations and constants with appropriate types to support contract expressions.",
    "Ensure that all visible identifiers used in AGREE expressions are properly scoped and typed.",
    "Link requirement expressions to visible features or named constants for semantic clarity.",
    "Validate that expression types match declared types to prevent annex errors."
  ],
  "syntax_or_pattern_reminders": [
    "Use `assume \"label\": expression;` for input constraints and `guarantee \"label\": expression;` for output constraints.",
    "Define helper equations with `eq name : type = expression;` to modularize complex logic."
  ],
  "anti_patterns": [
    "Avoid placing assumptions or guarantees without concrete bounds or visible feature references.",
    "Do not mix incompatible types in expressions without explicit casting or type alignment."
  ],
  "irrelevant_topics": [
    "model traceability",
    "requirement semantics",
    "validator diagnostics",
    "model fusion rules"
  ]
}