{
  "rag_rules": [
    "AGREE annex blocks must be placed in component implementation annexes for implementation-level bindings and assignments.",
    "Use assign statements in implementation scope only for existing output features or declared auxiliary variables."
  ],
  "generic_rules": [
    "AGREE contracts are encapsulated within annex agree {** ... **}; blocks.",
    "Component type annexes are for assumptions, guarantees, constants, and equations; implementation annexes are for bindings and assignments.",
    "AGREE scalar types must use int, real, or bool for declarations."
  ],
  "syntax_or_pattern_reminders": [
    "Assign statements in implementation scope must reference existing output features or declared auxiliary variables.",
    "AGREE contracts are enclosed in annex agree {** ... **}; blocks."
  ],
  "anti_patterns": [
    "Do not place guarantee statements in implementation scope.",
    "Do not use invalid scalar type names like 'integer' or 'boolean' in AGREE declarations."
  ],
  "irrelevant_topics": [
    "requirement traceability",
    "validator diagnostics",
    "assume/guarantee syntax",
    "model repair patterns"
  ]
}