{
  "rag_rules": [
    "Translate 'ecam_info == true when dps > 0' and 'ecam_info == false when dps <= 0' into AGREE guarantee clauses.",
    "Use AGREE logical operators (and, or, not, =>) to express the relationships between 'ecam_info' and 'dps'."
  ],
  "generic_rules": [
    "Express behavioral relations as AGREE guarantees.",
    "Use 'assume' for preconditions and 'guarantee' for postconditions.",
    "Use 'eq' for defining intermediate boolean variables."
  ],
  "syntax_or_pattern_reminders": [
    "AGREE types are 'int', 'real', and 'bool'.",
    "Use initialized temporal recurrence for stateful equations (e.g., `0.0 -> pre(t) + step`).",
    "Use `if ... then ... else` for branching logic."
  ],
  "anti_patterns": [
    "Do not include AADL property names (e.g., Compute_Execution_Time) directly as AGREE variables.",
    "Avoid unresolved references to 'integer' or 'boolean'; use 'int' and 'bool' instead."
  ],
  "irrelevant_topics": [
    "AADL scope notes regarding component type vs implementation scope",
    "Model fusion owner/scope rules",
    "Validator-driven minimal repair patterns"
  ]
}