{
  "problems": [
    {
      "diagnostic": "left and right sides of binary expression '=' are of type 'bool' and 'real', but must be of the same type",
      "cause": "AGREE does not support AADL type-membership expressions such as `x in Package::Type`",
      "minimal_edit": "Rewrite the expression to use only visible symbols and legal AGREE expressions"
    },
    {
      "diagnostic": "mismatched input '<' expecting ';'",
      "cause": "AGREE does not support AADL type-membership expressions such as `x in Package::Type`",
      "minimal_edit": "Rewrite the expression to use only visible symbols and legal AGREE expressions"
    }
  ],
  "repair_mode": "edit_annex",
  "executor_steps": [
    "Rewrite the expression to use only visible symbols and legal AGREE expressions",
    "Replace the expression with the rewritten expression"
  ]
}