{
  "rag_rules": [
    "Use `assign` for implementation-level output bindings only when the left-hand side is an existing output feature or declared auxiliary variable",
    "Place assumptions and guarantees in component type annexes only when concrete bounds or visible relations are provided"
  ],
  "generic_rules": [
    "AGREE annex blocks must be scoped to their owning component declaration",
    "AGREE expressions may only reference identifiers visible in the current component scope"
  ],
  "syntax_or_pattern_reminders": [
    "AGREE contracts are enclosed in `annex agree {** ... **};` blocks",
    "Use `assume` for preconditions, `guarantee` for postconditions, and `assign` for output bindings in implementation scope"
  ],
  "anti_patterns": [
    "Do not place guarantee statements in implementation scope",
    "Do not reference AADL property names as AGREE variables without explicit typed ports or constants"
  ],
  "irrelevant_topics": [
    "AADL property associations and timing properties",
    "Model fusion and component merging",
    "Validator diagnostics and repair patterns"
  ]
}