{
  "problems": [
    {
      "diagnostic": "/CaseProject/modified_model.aadl | line 84: no viable alternative at input '='",
      "cause": "Invalid syntax in AGREE guarantee statement",
      "minimal_edit": "Replace '=' with '==' in guarantee statement"
    },
    {
      "diagnostic": "/CaseProject/modified_model.aadl | line 84: right side of binary expression '/' is of type '<error>' but must be of type 'real'",
      "cause": "Invalid type in AGREE guarantee statement",
      "minimal_edit": "Replace '/' with a valid operator or remove the expression"
    },
    {
      "diagnostic": "/CaseProject/modified_model.aadl | line 89: no viable alternative at input '='",
      "cause": "Invalid syntax in AGREE guarantee statement",
      "minimal_edit": "Replace '=' with '==' in guarantee statement"
    },
    {
      "diagnostic": "/CaseProject/modified_model.aadl | line 89: right side of binary expression '/' is of type '<error>' but must be of type 'real'",
      "cause": "Invalid type in AGREE guarantee statement",
      "minimal_edit": "Replace '/' with a valid operator or remove the expression"
    },
    {
      "diagnostic": "/CaseProject/modified_model.aadl | line 113: Couldn't resolve reference to ConnectionEnd 'attitude_window'.",
      "cause": "Undefined connection end in AADL connection",
      "minimal_edit": "Define 'attitude_window' connection end or remove the connection"
    },
    {
      "diagnostic": "/CaseProject/modified_model.aadl | line 114: Couldn't resolve reference to ConnectionEnd 'check_thresholds'.",
      "cause": "Undefined connection end in AADL connection",
      "minimal_edit": "Define 'check_thresholds' connection end or remove the connection"
    }
  ],
  "repair_mode": "edit_annex",
  "executor_steps": [
    "Edit the AGREE annex to fix the syntax and type errors in the guarantee statements",
    "Define the missing connection ends 'attitude_window' and 'check_thresholds' or remove the connections"
  ]
}