{
  "problems": [
    {
      "diagnostic": "line 37: missing EOF at 'var'",
      "cause": "AGREE annex syntax error due to incomplete statement or missing semicolon",
      "minimal_edit": "Add semicolon after each variable declaration on lines 37-39"
    }
  ],
  "repair_mode": "edit_annex",
  "executor_steps": [
    "Add semicolon after 'var acc_out_data_x_aux : real' on line 37",
    "Add semicolon after 'var acc_out_data_y_aux : real' on line 38",
    "Add semicolon after 'var acc_out_data_z_aux : real' on line 39"
  ]
}