{
  "rag_rules": [
    "Use initialized temporal recurrence for stateful equations and nested if-then-else for branching logic in AGREE contracts.",
    "Place input assumptions and output guarantees in annex agree only when concrete bounds or visible relations are provided."
  ],
  "generic_rules": [
    "Use AGREE logical operators (and, or, not, =>) for contract expressions.",
    "Align helper declaration types with expression types to avoid type mismatches.",
    "Structure guarantees to reflect conditional relationships between boolean attributes and value constraints."
  ],
  "syntax_or_pattern_reminders": [
    "Equations in AGREE should declare a type and use valid logical operators.",
    "Guarantees should express conditional relationships using implication or conjunction."
  ],
  "anti_patterns": [
    "Avoid placing assumptions or guarantees in annex agree without concrete bounds or visible feature names.",
    "Do not mix type declarations with incorrect arithmetic or comparison types in helper equations."
  ],
  "irrelevant_topics": [
    "AADL structural extraction",
    "requirement semantics and traceability",
    "model fusion owner/scope rules",
    "validator-driven repair patterns"
  ]
}