{
  "problems": [
    {
      "diagnostic": "/CaseProject/modified_model.aadl | line 177: Assume statements are allowed only in component types",
      "cause": "Assume statements are placed in ADIRU.EMV2, which is a system implementation, not a component type",
      "minimal_edit": "Move the annex agree block from ADIRU.EMV2 to ADIRU"
    },
    {
      "diagnostic": "/CaseProject/modified_model.aadl | line 179: Assume statements are allowed only in component types",
      "cause": "Assume statements are placed in ADIRU.EMV2, which is a system implementation, not a component type",
      "minimal_edit": "Move the annex agree block from ADIRU.EMV2 to ADIRU"
    },
    {
      "diagnostic": "/CaseProject/modified_model.aadl | line 181: Assume statements are allowed only in component types",
      "cause": "Assume statements are placed in ADIRU.EMV2, which is a system implementation, not a component type",
      "minimal_edit": "Move the annex agree block from ADIRU.EMV2 to ADIRU"
    },
    {
      "diagnostic": "/CaseProject/modified_model.aadl | line 183: Assume statements are allowed only in component types",
      "cause": "Assume statements are placed in ADIRU.EMV2, which is a system implementation, not a component type",
      "minimal_edit": "Move the annex agree block from ADIRU.EMV2 to ADIRU"
    },
    {
      "diagnostic": "/CaseProject/modified_model.aadl | line 185: Assume statements are allowed only in component types",
      "cause": "Assume statements are placed in ADIRU.EMV2, which is a system implementation, not a component type",
      "minimal_edit": "Move the annex agree block from ADIRU.EMV2 to ADIRU"
    },
    {
      "diagnostic": "/CaseProject/modified_model.aadl | line 187: Assume statements are allowed only in component types",
      "cause": "Assume statements are placed in ADIRU.EMV2, which is a system implementation, not a component type",
      "minimal_edit": "Move the annex agree block from ADIRU.EMV2 to ADIRU"
    }
  ],
  "repair_mode": "edit_full_model",
  "executor_steps": [
    "Remove the annex agree block from ADIRU.EMV2",
    "Add an annex agree block at the ADIRU system level (not implementation) with the same assume statements"
  ]
}