{
  "rag_rules": [
    "Place assumptions and guarantees referencing component ports within the component type scope.",
    "Place implementation-level bindings within the implementation scope."
  ],
  "generic_rules": [
    "AGREE contracts reside within `annex agree { ... };` blocks.",
    "Use the AADL model as the authoritative source for component structure.",
    "Input envelope assumptions and output range guarantees should use concrete bounds or visible relations."
  ],
  "syntax_or_pattern_reminders": [
    "Ensure AGREE expressions align with AADL data types (bool, int, real).",
    "Use exact Boolean expressions only for AGREE bool ports; avoid numeric conversions."
  ],
  "anti_patterns": [
    "Do not use AADL properties (e.g., Compute_Execution_Time) directly in AGREE expressions without corresponding ports or constants.",
    "Avoid using implementation-only subcomponent paths in component type annexes."
  ],
  "irrelevant_topics": [
    "AGREE clause generation details",
    "Assume/guarantee syntax specifics",
    "Validator diagnostics",
    "Repair patterns"
  ]
}